allauth_socialaccount_provider_keycloak/__init__.py
allauth_socialaccount_provider_keycloak/apps.py
allauth_socialaccount_provider_keycloak/provider.py
allauth_socialaccount_provider_keycloak/tests.py
allauth_socialaccount_provider_keycloak/urls.py
allauth_socialaccount_provider_keycloak/views.py
allauth_socialaccount_provider_keycloak-0.1.2.dist-info/LICENSE
allauth_socialaccount_provider_keycloak-0.1.2.dist-info/METADATA
allauth_socialaccount_provider_keycloak-0.1.2.dist-info/WHEEL
allauth_socialaccount_provider_keycloak-0.1.2.dist-info/top_level.txt
allauth_socialaccount_provider_keycloak-0.1.2.dist-info/RECORD
