Metadata-Version: 2.1
Name: allauth-socialaccount-provider-keycloak
Version: 0.1.2
Summary: allauth oauth2 provider for Keycloak
Home-page: https://github.com/fherdom/allauth-socialaccount-provider-keycloak
Author: Félix José Hernández
Author-email: info@felixjosehernandez.es
License: UNKNOWN
Platform: UNKNOWN
Classifier: Programming Language :: Python :: 3
Classifier: License :: OSI Approved :: MIT License
Classifier: Operating System :: OS Independent
Requires-Python: >=3.6
